[{"fields": {"name": "A&E [ARG]"}, "model": "thumbs.channel", "pk": 1}, {"fields": {"name": "Am\u00e9rica 24 [ARG]"}, "model": "thumbs.channel", "pk": 2}, {"fields": {"name": "Am\u00e9rica 2 [ARG]"}, "model": "thumbs.channel", "pk": 3}, {"fields": {"name": "Am\u00e9rica 2 SAT [ARG]"}, "model": "thumbs.channel", "pk": 4}, {"fields": {"name": "Am\u00e9rica PLACAS"}, "model": "thumbs.channel", "pk": 5}, {"fields": {"name": "Animal Planet [ARG]"}, "model": "thumbs.channel", "pk": 6}, {"fields": {"name": "Axn [Cono Sur]"}, "model": "thumbs.channel", "pk": 7}, {"fields": {"name": "C5N [ARG]"}, "model": "thumbs.channel", "pk": 8}, {"fields": {"name": "Canal 10 C\u00f3rdoba [ARG]"}, "model": "thumbs.channel", "pk": 9}, {"fields": {"name": "Canal 10 Rio Negro [ARG]"}, "model": "thumbs.channel", "pk": 10}, {"fields": {"name": "Canal 10 Tucum\u00e1n [ARG]"}, "model": "thumbs.channel", "pk": 11}, {"fields": {"name": "Canal 11 Salta [ARG]"}, "model": "thumbs.channel", "pk": 12}, {"fields": {"name": "Canal 11 Salta [ARG][SAT]"}, "model": "thumbs.channel", "pk": 13}, {"fields": {"name": "Canal 12 C\u00f3rdoba [ARG]"}, "model": "thumbs.channel", "pk": 14}, {"fields": {"name": "Canal 13 [ARG]"}, "model": "thumbs.channel", "pk": 15}, {"fields": {"name": "Canal 13 Corrientes [ARG]"}, "model": "thumbs.channel", "pk": 16}, {"fields": {"name": "Canal 13 SAT [ARG]"}, "model": "thumbs.channel", "pk": 17}, {"fields": {"name": "Canal 26 [ARG]"}, "model": "thumbs.channel", "pk": 18}, {"fields": {"name": "Canal 3 Rosario [ARG]"}, "model": "thumbs.channel", "pk": 19}, {"fields": {"name": "Canal 5 Rosario [ARG]"}, "model": "thumbs.channel", "pk": 20}, {"fields": {"name": "Canal 5 San Juan [ARG]"}, "model": "thumbs.channel", "pk": 21}, {"fields": {"name": "Canal 7 [ARG]"}, "model": "thumbs.channel", "pk": 22}, {"fields": {"name": "Canal 7 Mendoza [ARG]"}, "model": "thumbs.channel", "pk": 23}, {"fields": {"name": "Canal 7 Neuqu\u00e9n [ARG]"}, "model": "thumbs.channel", "pk": 24}, {"fields": {"name": "Canal 8 C\u00f3rdoba [ARG]"}, "model": "thumbs.channel", "pk": 25}, {"fields": {"name": "Canal 8 Mar del Plata [ARG]"}, "model": "thumbs.channel", "pk": 26}, {"fields": {"name": "Canal 8 San Juan [ARG]"}, "model": "thumbs.channel", "pk": 27}, {"fields": {"name": "Canal 8 Tucum\u00e1n [ARG]"}, "model": "thumbs.channel", "pk": 28}, {"fields": {"name": "Canal 9 [ARG]"}, "model": "thumbs.channel", "pk": 29}, {"fields": {"name": "Canal 9 Cv"}, "model": "thumbs.channel", "pk": 30}, {"fields": {"name": "Canal 9 Mendoza  [ARG]"}, "model": "thumbs.channel", "pk": 31}, {"fields": {"name": "Canal 9 PLACAS"}, "model": "thumbs.channel", "pk": 32}, {"fields": {"name": "Canal 9 Resistencia [ARG]"}, "model": "thumbs.channel", "pk": 33}, {"fields": {"name": "Canal 9 Salta [ARG]"}, "model": "thumbs.channel", "pk": 34}, {"fields": {"name": "Canal 9 SAT [ARG]"}, "model": "thumbs.channel", "pk": 35}, {"fields": {"name": "Canal C"}, "model": "thumbs.channel", "pk": 36}, {"fields": {"name": "Casa Club"}, "model": "thumbs.channel", "pk": 37}, {"fields": {"name": "Cinecanal [ARG]"}, "model": "thumbs.channel", "pk": 38}, {"fields": {"name": "CN23 [ARG]"}, "model": "thumbs.channel", "pk": 39}, {"fields": {"name": "Cosmopolitan TV [LATS]"}, "model": "thumbs.channel", "pk": 40}, {"fields": {"name": "Cr\u00f3nica TV [ARG]"}, "model": "thumbs.channel", "pk": 41}, {"fields": {"name": "Direct Sports ARG - Placa"}, "model": "thumbs.channel", "pk": 42}, {"fields": {"name": "DIRECTV Live"}, "model": "thumbs.channel", "pk": 43}, {"fields": {"name": "DIRECTV Sport 111 [VEN]"}, "model": "thumbs.channel", "pk": 44}, {"fields": {"name": "DIRECTV Sport 2 612 [LAT]"}, "model": "thumbs.channel", "pk": 45}, {"fields": {"name": "DIRECTV Sport 610 [ARG]"}, "model": "thumbs.channel", "pk": 46}, {"fields": {"name": "DIRECTV Sport 610 [ECU]"}, "model": "thumbs.channel", "pk": 47}, {"fields": {"name": "DIRECTV Sport + 613 [LAT]"}, "model": "thumbs.channel", "pk": 48}, {"fields": {"name": "DIRECTV Sport 614 [LAT]"}, "model": "thumbs.channel", "pk": 49}, {"fields": {"name": "DIRECTV Sport 615 [LAT]"}, "model": "thumbs.channel", "pk": 50}, {"fields": {"name": "DIRECTV Sport 616 [LAT]"}, "model": "thumbs.channel", "pk": 51}, {"fields": {"name": "DIRECTV Sport 617 [LAT]"}, "model": "thumbs.channel", "pk": 52}, {"fields": {"name": "DIRECTV Sport 619 [LAT]"}, "model": "thumbs.channel", "pk": 53}, {"fields": {"name": "DIRECTV Sport 635 [ECU]"}, "model": "thumbs.channel", "pk": 54}, {"fields": {"name": "DIRECTV Sport 658 [LAT]"}, "model": "thumbs.channel", "pk": 55}, {"fields": {"name": "DIRECTV Sport Especial 614 [LAT]"}, "model": "thumbs.channel", "pk": 56}, {"fields": {"name": "DIRECTV Sport Pan 1610 [LAT]"}, "model": "thumbs.channel", "pk": 57}, {"fields": {"name": "DIRECTV Sports 111 [VEN]"}, "model": "thumbs.channel", "pk": 58}, {"fields": {"name": "DIRECTV Sports 2 612 [LAT]"}, "model": "thumbs.channel", "pk": 59}, {"fields": {"name": "Directv Sports 2 - Placa"}, "model": "thumbs.channel", "pk": 60}, {"fields": {"name": "DIRECTV Sports 610 [ARG]"}, "model": "thumbs.channel", "pk": 61}, {"fields": {"name": "DIRECTV Sports + 613 [LAT]"}, "model": "thumbs.channel", "pk": 62}, {"fields": {"name": "DIRECTV Sports Especial 616 [LAT]"}, "model": "thumbs.channel", "pk": 63}, {"fields": {"name": "DIRECTV Sports Pan 1610 [LAT]"}, "model": "thumbs.channel", "pk": 64}, {"fields": {"name": "Discovery Channel [ARG]"}, "model": "thumbs.channel", "pk": 65}, {"fields": {"name": "Discovery H&H [ARG]"}, "model": "thumbs.channel", "pk": 66}, {"fields": {"name": "Discovery Travel & Living [ARG]"}, "model": "thumbs.channel", "pk": 67}, {"fields": {"name": "E! Entertainment [ARG]"}, "model": "thumbs.channel", "pk": 68}, {"fields": {"name": "El Gourmet.com [ARG]"}, "model": "thumbs.channel", "pk": 69}, {"fields": {"name": "ESPN"}, "model": "thumbs.channel", "pk": 70}, {"fields": {"name": "ESPN+ [ARG]"}, "model": "thumbs.channel", "pk": 71}, {"fields": {"name": "ESPN Extra"}, "model": "thumbs.channel", "pk": 72}, {"fields": {"name": "ESPN MAS [ARG]"}, "model": "thumbs.channel", "pk": 73}, {"fields": {"name": "Europa Europa [LATS]"}, "model": "thumbs.channel", "pk": 74}, {"fields": {"name": "Film & Arts"}, "model": "thumbs.channel", "pk": 75}, {"fields": {"name": "Fox [LATE]"}, "model": "thumbs.channel", "pk": 76}, {"fields": {"name": "Fox Life [LAT]"}, "model": "thumbs.channel", "pk": 77}, {"fields": {"name": "Fox Sports [ARG]"}, "model": "thumbs.channel", "pk": 78}, {"fields": {"name": "FX [ARG]"}, "model": "thumbs.channel", "pk": 79}, {"fields": {"name": "FX Channel DTV"}, "model": "thumbs.channel", "pk": 80}, {"fields": {"name": "Golf Channel 628 [LAT]"}, "model": "thumbs.channel", "pk": 81}, {"fields": {"name": "Golf Channel [LATS]"}, "model": "thumbs.channel", "pk": 82}, {"fields": {"name": "Golf Channel - Placa"}, "model": "thumbs.channel", "pk": 83}, {"fields": {"name": "History [ARG]"}, "model": "thumbs.channel", "pk": 84}, {"fields": {"name": "Investigation Discovery [ARG]"}, "model": "thumbs.channel", "pk": 85}, {"fields": {"name": "Liv"}, "model": "thumbs.channel", "pk": 86}, {"fields": {"name": "Magazine [ARG]"}, "model": "thumbs.channel", "pk": 87}, {"fields": {"name": "Metro"}, "model": "thumbs.channel", "pk": 88}, {"fields": {"name": "MGM [LAT]"}, "model": "thumbs.channel", "pk": 89}, {"fields": {"name": "Nat Geo [LATE]"}, "model": "thumbs.channel", "pk": 90}, {"fields": {"name": "On DIRECTV 211 [LAT]"}, "model": "thumbs.channel", "pk": 91}, {"fields": {"name": "On DIRECTV HD 211 [LAT]"}, "model": "thumbs.channel", "pk": 92}, {"fields": {"name": "On DIrectv - Placa"}, "model": "thumbs.channel", "pk": 93}, {"fields": {"name": "Patrones"}, "model": "thumbs.channel", "pk": 94}, {"fields": {"name": "Patrones Barney"}, "model": "thumbs.channel", "pk": 95}, {"fields": {"name": "Patrones Bart"}, "model": "thumbs.channel", "pk": 96}, {"fields": {"name": "Quiero! [LAT]"}, "model": "thumbs.channel", "pk": 97}, {"fields": {"name": "SKYSports"}, "model": "thumbs.channel", "pk": 98}, {"fields": {"name": "Space"}, "model": "thumbs.channel", "pk": 99}, {"fields": {"name": "SporTV"}, "model": "thumbs.channel", "pk": 100}, {"fields": {"name": "Telef\u00e9 [ARG]"}, "model": "thumbs.channel", "pk": 101}, {"fields": {"name": "Telef\u00e9 Interior [ARG]"}, "model": "thumbs.channel", "pk": 102}, {"fields": {"name": "TN Todo Noticias [ARG]"}, "model": "thumbs.channel", "pk": 103}, {"fields": {"name": "TyC Sports [ARG]"}, "model": "thumbs.channel", "pk": 104}, {"fields": {"name": "Universal Channel [ARG]"}, "model": "thumbs.channel", "pk": 105}, {"fields": {"name": "Volver [ARG]"}, "model": "thumbs.channel", "pk": 106}, {"fields": {"name": "Warner Channel"}, "model": "thumbs.channel", "pk": 107}, {"fields": {"name": "WC DTVS [ARG]"}, "model": "thumbs.channel", "pk": 108}, {"fields": {"name": "WC DTVS Cancha + [LAT]"}, "model": "thumbs.channel", "pk": 109}, {"fields": {"name": "WC DTVS Especial 617 [LAT]"}, "model": "thumbs.channel", "pk": 110}, {"fields": {"name": "WC DTVS Pan [LAT]"}, "model": "thumbs.channel", "pk": 111}, {"fields": {"name": "WC DTVS [VEN]"}, "model": "thumbs.channel", "pk": 112}]